README.md
setup.py
bin/immpload
immpload/__init__.py
immpload/defaults.py
immpload/munger.py
immpload/templates.py
immpload/validators.py
immpload.egg-info/PKG-INFO
immpload.egg-info/SOURCES.txt
immpload.egg-info/dependency_links.txt
immpload.egg-info/requires.txt
immpload.egg-info/top_level.txt