Metadata-Version: 2.1
Name: immpload
Version: 1.1.2
Summary: Immport upload preparation
Home-page: https://github.com/biodev/imppload/
Author: Oregon Health & Sciences University
Author-email: loneyf@ohsu.edu
License: MIT
Keywords: Immpload
Platform: Any
Classifier: Development Status :: 5 - Production/Stable
Classifier: Topic :: Scientific/Engineering :: Bio-Informatics
Classifier: Environment :: Console
Classifier: Intended Audience :: Science/Research
Classifier: License :: OSI Approved :: MIT License
Classifier: Operating System :: OS Independent
Classifier: Programming Language :: Python
Classifier: Programming Language :: Python :: 3
